{
  "$schema": "https://json-schema.org/draft/2020-12/schema",
  "$id": "telerivet/Broadcast",
  "title": "Broadcast",
  "x-openfn-adaptor": "telerivet",
  "x-source": {
    "openapi": "#/components/schemas/Broadcast",
    "capturedAt": "2026-07-06"
  },
  "type": "object",
  "description": "A Telerivet broadcast object.",
  "properties": {
    "id": {
      "type": "string"
    },
    "object": {
      "type": "string",
      "example": "broadcast"
    },
    "recipients": {
      "type": "array",
      "items": {
        "type": "object",
        "additionalProperties": true
      }
    },
    "title": {
      "type": [
        "string",
        "null"
      ]
    },
    "time_created": {
      "type": "integer"
    },
    "last_message_time": {
      "type": [
        "integer",
        "null"
      ]
    },
    "status": {
      "type": "string"
    },
    "message_type": {
      "type": "string",
      "example": "sms"
    },
    "content": {
      "type": [
        "string",
        "null"
      ]
    },
    "message_count": {
      "type": "integer"
    },
    "estimated_count": {
      "type": "integer"
    },
    "vars": {
      "type": "object",
      "additionalProperties": true
    },
    "project_id": {
      "type": "string"
    }
  }
}
