{
  "adaptor": "zata",
  "capturedAt": "2026-07-06",
  "dialect": "https://json-schema.org/draft/2020-12/schema",
  "source": "openapi.json",
  "resources": [
    "AuthResponse",
    "Bank",
    "Branch",
    "Company",
    "Expense",
    "HealthStatus",
    "LookupItem",
    "Party",
    "PaymentResponse",
    "Product",
    "TransactionItem",
    "TransactionTotals"
  ],
  "objects": [
    {
      "name": "AuthResponse",
      "file": "AuthResponse.json",
      "resource": true
    },
    {
      "name": "Bank",
      "file": "Bank.json",
      "resource": true
    },
    {
      "name": "Branch",
      "file": "Branch.json",
      "resource": true
    },
    {
      "name": "Company",
      "file": "Company.json",
      "resource": true
    },
    {
      "name": "Expense",
      "file": "Expense.json",
      "resource": true
    },
    {
      "name": "HealthStatus",
      "file": "HealthStatus.json",
      "resource": true
    },
    {
      "name": "LookupItem",
      "file": "LookupItem.json",
      "resource": true
    },
    {
      "name": "Party",
      "file": "Party.json",
      "resource": true
    },
    {
      "name": "PaymentResponse",
      "file": "PaymentResponse.json",
      "resource": true
    },
    {
      "name": "Product",
      "file": "Product.json",
      "resource": true
    },
    {
      "name": "TransactionItem",
      "file": "TransactionItem.json",
      "resource": true
    },
    {
      "name": "TransactionTotals",
      "file": "TransactionTotals.json",
      "resource": true
    },
    {
      "name": "User",
      "file": "User.json",
      "resource": false
    }
  ]
}
