{
  "$schema": "https://json-schema.org/draft/2020-12/schema",
  "$id": "magpi/SurveyData",
  "title": "SurveyData",
  "x-openfn-adaptor": "magpi",
  "x-source": {
    "openapi": "#/components/schemas/SurveyData",
    "capturedAt": "2026-07-06"
  },
  "type": "object",
  "description": "A single survey submission. Answer fields are dynamic per form, so arbitrary string-valued properties are permitted alongside the well-known metadata fields.",
  "properties": {
    "SubmissionId": {
      "type": "string",
      "description": "Unique identifier of the submission.",
      "example": "9911002"
    },
    "SubmissionDate": {
      "type": "string",
      "description": "Timestamp the submission was received.",
      "example": "2017-09-28 14:03:11"
    },
    "LastSubmissionDate": {
      "type": "string",
      "description": "Timestamp of the most recent submission in the list; the adaptor stores this as state.lastSubmissionDate for incremental fetches.",
      "example": "2017-10-01 09:15:00"
    },
    "surveyId": {
      "type": "string",
      "description": "Survey identifier, stamped onto each record by the adaptor.",
      "example": "37479"
    },
    "source": {
      "type": "string",
      "description": "Source label stamped onto each record by the adaptor.",
      "example": "Magpi API"
    }
  },
  "additionalProperties": {
    "type": "string",
    "description": "Form-specific answer values keyed by question/field name."
  }
}
