{
  "res.partner": {
    "1": {
      "id": 1,
      "name": "Kamara Household",
      "spp_id": "GRP_KAMARA01",
      "is_group": true,
      "is_registrant": true,
      "kind": "Household",
      "area_id": [
        2,
        "Bo District"
      ]
    },
    "2": {
      "id": 2,
      "name": "Sesay Household",
      "spp_id": "GRP_SESAY001",
      "is_group": true,
      "is_registrant": true,
      "kind": "Household",
      "area_id": [
        3,
        "Kenema District"
      ]
    },
    "3": {
      "id": 3,
      "name": "Amina Kamara",
      "spp_id": "IND_AMINA001",
      "is_group": false,
      "is_registrant": true,
      "gender": "Female",
      "birthdate": "1985-09-30",
      "phone": "+23276000002"
    },
    "4": {
      "id": 4,
      "name": "Mohamed Kamara",
      "spp_id": "IND_MOHAMED1",
      "is_group": false,
      "is_registrant": true,
      "gender": "Male",
      "birthdate": "1982-05-14",
      "phone": "+23276000004"
    },
    "5": {
      "id": 5,
      "name": "Fatmata Sesay",
      "spp_id": "IND_FATMATA1",
      "is_group": false,
      "is_registrant": true,
      "gender": "Female",
      "birthdate": "1990-02-20",
      "phone": "+23276000005"
    }
  },
  "g2p.program": {
    "10": {
      "id": 10,
      "name": "Cash Transfer 2024",
      "program_id": "PROG_CT2024",
      "program_type": "cash",
      "state": "active"
    },
    "11": {
      "id": 11,
      "name": "School Feeding",
      "program_id": "PROG_SF2024",
      "program_type": "in_kind",
      "state": "active"
    }
  },
  "spp.area": {
    "1": {
      "id": 1,
      "name": "Sierra Leone",
      "spp_id": "AREA_SL",
      "code": "SL",
      "parent_id": false
    },
    "2": {
      "id": 2,
      "name": "Bo District",
      "spp_id": "AREA_SL_BO",
      "code": "SL-BO",
      "parent_id": [
        1,
        "Sierra Leone"
      ]
    },
    "3": {
      "id": 3,
      "name": "Kenema District",
      "spp_id": "AREA_SL_KE",
      "code": "SL-KE",
      "parent_id": [
        1,
        "Sierra Leone"
      ]
    }
  },
  "spp.service.point": {
    "20": {
      "id": 20,
      "name": "Bo Pay Point",
      "spp_id": "SVP_BO01",
      "area_id": [
        2,
        "Bo District"
      ],
      "service_type_ids": [
        1
      ],
      "phone_sanitized": "+23276111020",
      "shop_address": "Bo Town Centre",
      "is_contract_active": true,
      "is_disabled": false
    },
    "21": {
      "id": 21,
      "name": "Kenema Pay Point",
      "spp_id": "SVP_KE01",
      "area_id": [
        3,
        "Kenema District"
      ],
      "service_type_ids": [
        2
      ],
      "phone_sanitized": "+23276111021",
      "shop_address": "Kenema Market",
      "is_contract_active": true,
      "is_disabled": false
    }
  },
  "g2p.program_membership": {
    "30": {
      "id": 30,
      "partner_id": [
        1,
        "Kamara Household"
      ],
      "program_id": [
        10,
        "Cash Transfer 2024"
      ],
      "state": "enrolled"
    }
  },
  "g2p.group.membership": {
    "40": {
      "id": 40,
      "group": [
        1,
        "Kamara Household"
      ],
      "individual": [
        3,
        "Amina Kamara"
      ],
      "kind": [
        1
      ],
      "is_ended": false,
      "start_date": "2024-01-15",
      "ended_date": false,
      "individual_birthdate": "1985-09-30",
      "individual_gender": "Female"
    },
    "41": {
      "id": 41,
      "group": [
        1,
        "Kamara Household"
      ],
      "individual": [
        4,
        "Mohamed Kamara"
      ],
      "kind": [],
      "is_ended": false,
      "start_date": "2024-01-15",
      "ended_date": false,
      "individual_birthdate": "1982-05-14",
      "individual_gender": "Male"
    }
  },
  "g2p.group.membership.kind": {
    "1": {
      "id": 1,
      "name": "Head",
      "is_unique": true
    }
  }
}
