{
  "$schema": "https://json-schema.org/draft/2020-12/schema",
  "$id": "primero/Form",
  "title": "Form",
  "x-openfn-adaptor": "primero",
  "x-source": {
    "openapi": "#/components/schemas/Form",
    "capturedAt": "2026-07-06"
  },
  "type": "object",
  "properties": {
    "id": {
      "type": "integer"
    },
    "unique_id": {
      "type": "string"
    },
    "name": {
      "type": "object",
      "additionalProperties": {
        "type": "string"
      }
    },
    "parent_form": {
      "type": "string"
    },
    "visible": {
      "type": "boolean"
    }
  }
}
